{"textures":{"1":"modelengine:entity/hp3_werewolf"},"elements":[{"from":[3.0,3.8973217,1.9291248],"to":[13.0,15.897322,9.929125],"faces":{"east":{"uv":[4.5,4.0,3.5,5.5],"tintindex":0,"rotation":0,"texture":"#1"},"south":{"uv":[1.25,2.5,2.5,4.0],"tintindex":0,"rotation":0,"texture":"#1"},"north":{"uv":[0.0,2.5,1.25,4.0],"tintindex":0,"rotation":0,"texture":"#1"},"west":{"uv":[3.5,4.0,4.5,5.5],"tintindex":0,"rotation":0,"texture":"#1"},"up":{"uv":[3.25,6.5,2.0,5.5],"tintindex":0,"rotation":0,"texture":"#1"},"down":{"uv":[4.5,5.5,3.25,6.5],"tintindex":0,"rotation":0,"texture":"#1"}}},{"from":[3.765367,3.8973217,9.776884],"to":[3.765367,15.897322,13.776884],"faces":{"east":{"uv":[5.75,8.0,5.25,9.5],"tintindex":0,"rotation":0,"texture":"#1"},"west":{"uv":[5.25,8.0,5.75,9.5],"tintindex":0,"rotation":0,"texture":"#1"}},"rotation":{"origin":[3.765367,9.897322,11.776884],"angle":22.5,"axis":"y"}},{"from":[5.0,1.5802965,2.3900099],"to":[11.0,5.5802956,10.39001],"faces":{"east":{"uv":[9.125,5.625,10.125,6.125],"tintindex":0,"rotation":0,"texture":"#1"},"south":{"uv":[5.5,10.25,6.25,10.75],"tintindex":0,"rotation":0,"texture":"#1"},"north":{"uv":[10.25,4.375,11.0,4.875],"tintindex":0,"rotation":0,"texture":"#1"},"west":{"uv":[9.25,4.5,10.25,5.0],"tintindex":0,"rotation":0,"texture":"#1"},"up":{"uv":[8.75,3.5,8.0,2.5],"tintindex":0,"rotation":0,"texture":"#1"},"down":{"uv":[8.75,3.5,8.0,4.5],"tintindex":0,"rotation":0,"texture":"#1"}},"rotation":{"origin":[12.0,3.5802965,6.39001],"angle":-22.5,"axis":"x"}},{"from":[12.2346325,3.8973217,9.776884],"to":[12.2346325,15.897322,13.776884],"faces":{"east":{"uv":[5.75,8.0,5.25,9.5],"tintindex":0,"rotation":0,"texture":"#1"},"west":{"uv":[5.25,8.0,5.75,9.5],"tintindex":0,"rotation":0,"texture":"#1"}},"rotation":{"origin":[12.2346325,9.897322,11.776884],"angle":-22.5,"axis":"y"}}]}