{"textures":{"0":"modelengine:entity/hp3_cauldron_monster"},"elements":[{"from":[-5.5,13.794117,6.1911764],"to":[-5.0,15.794117,8.191176],"faces":{"east":{"uv":[16.0,3.1875,15.75,3.4375],"tintindex":0,"rotation":0,"texture":"#0"},"south":{"uv":[15.375,3.1875,15.3125,3.4375],"tintindex":0,"rotation":0,"texture":"#0"},"north":{"uv":[15.5,3.1875,15.4375,3.4375],"tintindex":0,"rotation":0,"texture":"#0"},"west":{"uv":[15.75,3.1875,15.5,3.4375],"tintindex":0,"rotation":0,"texture":"#0"},"up":{"uv":[15.5,3.1875,15.75,3.125],"tintindex":0,"rotation":90,"texture":"#0"},"down":{"uv":[15.75,3.1875,16.0,3.125],"tintindex":0,"rotation":270,"texture":"#0"}},"rotation":{"origin":[-8.375,15.294117,5.1911764],"angle":-22.5,"axis":"x"}},{"from":[9.0,12.044117,19.941177],"to":[19.5,15.544117,20.941177],"faces":{"east":{"uv":[15.875,4.5625,15.75,5.0],"tintindex":0,"rotation":0,"texture":"#0"},"south":{"uv":[16.0,4.0,14.6875,4.4375],"tintindex":0,"rotation":0,"texture":"#0"},"north":{"uv":[16.0,3.5625,14.6875,4.0],"tintindex":0,"rotation":0,"texture":"#0"},"west":{"uv":[16.0,4.5625,15.875,5.0],"tintindex":0,"rotation":0,"texture":"#0"},"up":{"uv":[14.6875,4.5625,16.0,4.4375],"tintindex":0,"rotation":0,"texture":"#0"},"down":{"uv":[14.6875,3.5625,16.0,3.4375],"tintindex":0,"rotation":0,"texture":"#0"}},"rotation":{"origin":[14.25,13.794117,20.816177],"angle":-22.5,"axis":"z"}},{"from":[21.0,13.794117,6.1911764],"to":[21.5,15.794117,8.191176],"faces":{"east":{"uv":[15.5,3.1875,15.75,3.4375],"tintindex":0,"rotation":0,"texture":"#0"},"south":{"uv":[15.3125,3.1875,15.375,3.4375],"tintindex":0,"rotation":0,"texture":"#0"},"north":{"uv":[15.4375,3.1875,15.5,3.4375],"tintindex":0,"rotation":0,"texture":"#0"},"west":{"uv":[15.75,3.1875,16.0,3.4375],"tintindex":0,"rotation":0,"texture":"#0"},"up":{"uv":[15.5,3.125,15.75,3.1875],"tintindex":0,"rotation":90,"texture":"#0"},"down":{"uv":[15.75,3.125,16.0,3.1875],"tintindex":0,"rotation":270,"texture":"#0"}},"rotation":{"origin":[24.375,15.294117,5.1911764],"angle":-22.5,"axis":"x"}},{"from":[-7.0,20.044117,7.4411764],"to":[-4.0,22.544117,9.941176],"faces":{"east":{"uv":[5.3125,10.1875,5.0,10.5],"tintindex":0,"rotation":0,"texture":"#0"},"south":{"uv":[10.5625,1.125,10.1875,1.4375],"tintindex":0,"rotation":0,"texture":"#0"},"north":{"uv":[6.0,4.9375,5.625,5.25],"tintindex":0,"rotation":0,"texture":"#0"},"west":{"uv":[5.0,10.1875,4.6875,10.5],"tintindex":0,"rotation":0,"texture":"#0"},"up":{"uv":[10.1875,1.75,10.5625,1.4375],"tintindex":0,"rotation":0,"texture":"#0"},"down":{"uv":[10.1875,1.75,10.5625,2.0625],"tintindex":0,"rotation":0,"texture":"#0"}}},{"from":[21.0,13.455923,19.617382],"to":[21.5,15.455923,21.617382],"faces":{"east":{"uv":[15.5,3.1875,15.75,3.4375],"tintindex":0,"rotation":0,"texture":"#0"},"south":{"uv":[15.3125,3.1875,15.375,3.4375],"tintindex":0,"rotation":0,"texture":"#0"},"north":{"uv":[15.4375,3.1875,15.5,3.4375],"tintindex":0,"rotation":0,"texture":"#0"},"west":{"uv":[15.75,3.1875,16.0,3.4375],"tintindex":0,"rotation":0,"texture":"#0"},"up":{"uv":[15.5,3.125,15.75,3.1875],"tintindex":0,"rotation":90,"texture":"#0"},"down":{"uv":[15.75,3.125,16.0,3.1875],"tintindex":0,"rotation":270,"texture":"#0"}},"rotation":{"origin":[20.875,11.955923,14.117381],"angle":-45.0,"axis":"x"}},{"from":[23.0,19.044117,6.4411764],"to":[24.0,23.544117,10.941176],"faces":{"east":{"uv":[9.3125,8.875,9.875,9.4375],"tintindex":0,"rotation":0,"texture":"#0"},"south":{"uv":[5.875,8.0625,6.0,8.625],"tintindex":0,"rotation":0,"texture":"#0"},"north":{"uv":[5.875,7.5,6.0,8.0625],"tintindex":0,"rotation":0,"texture":"#0"},"west":{"uv":[9.4375,8.0625,10.0,8.625],"tintindex":0,"rotation":0,"texture":"#0"},"up":{"uv":[4.1875,9.5625,4.0625,9.0],"tintindex":0,"rotation":0,"texture":"#0"},"down":{"uv":[1.6875,9.0625,1.5625,9.625],"tintindex":0,"rotation":0,"texture":"#0"}}},{"from":[-2.5,26.544117,-2.5588236],"to":[-0.5,29.044117,18.441177],"faces":{"east":{"uv":[8.0625,6.9375,10.6875,7.25],"tintindex":0,"rotation":0,"texture":"#0"},"south":{"uv":[9.75,10.1875,10.0,10.5],"tintindex":0,"rotation":0,"texture":"#0"},"north":{"uv":[10.1875,8.5625,10.4375,8.875],"tintindex":0,"rotation":0,"texture":"#0"},"west":{"uv":[8.0625,7.25,10.6875,7.5625],"tintindex":0,"rotation":0,"texture":"#0"},"up":{"uv":[4.6875,10.5625,4.4375,7.9375],"tintindex":0,"rotation":0,"texture":"#0"},"down":{"uv":[1.9375,8.25,1.6875,10.875],"tintindex":0,"rotation":0,"texture":"#0"}}},{"from":[0.5,22.544117,-4.0588236],"to":[6.0,26.544117,-0.5588236],"faces":{"east":{"uv":[0.875,10.0,1.3125,10.5],"tintindex":0,"rotation":0,"texture":"#0"},"south":{"uv":[5.875,9.0,6.5625,9.5],"tintindex":0,"rotation":0,"texture":"#0"},"north":{"uv":[8.75,8.0625,9.4375,8.5625],"tintindex":0,"rotation":0,"texture":"#0"},"west":{"uv":[10.0,4.4375,10.4375,4.9375],"tintindex":0,"rotation":0,"texture":"#0"},"up":{"uv":[10.1875,1.1875,9.5,0.75],"tintindex":0,"rotation":0,"texture":"#0"},"down":{"uv":[10.1875,1.1875,9.5,1.625],"tintindex":0,"rotation":0,"texture":"#0"}}},{"from":[10.0,22.544117,-4.0588236],"to":[15.5,26.544117,-0.5588236],"faces":{"east":{"uv":[10.0,8.0625,10.4375,8.5625],"tintindex":0,"rotation":0,"texture":"#0"},"south":{"uv":[0.875,9.0625,1.5625,9.5625],"tintindex":0,"rotation":0,"texture":"#0"},"north":{"uv":[6.5625,9.0,7.25,9.5],"tintindex":0,"rotation":0,"texture":"#0"},"west":{"uv":[9.3125,10.0,9.75,10.5],"tintindex":0,"rotation":0,"texture":"#0"},"up":{"uv":[7.25,9.9375,6.5625,9.5],"tintindex":0,"rotation":0,"texture":"#0"},"down":{"uv":[1.5625,9.5625,0.875,10.0],"tintindex":0,"rotation":0,"texture":"#0"}}},{"from":[16.75,12.794117,20.941177],"to":[18.75,14.794117,21.441177],"faces":{"east":{"uv":[15.375,3.1875,15.3125,3.4375],"tintindex":0,"rotation":0,"texture":"#0"},"south":{"uv":[15.75,3.1875,15.5,3.4375],"tintindex":0,"rotation":0,"texture":"#0"},"north":{"uv":[16.0,3.1875,15.75,3.4375],"tintindex":0,"rotation":0,"texture":"#0"},"west":{"uv":[15.5,3.1875,15.4375,3.4375],"tintindex":0,"rotation":0,"texture":"#0"},"up":{"uv":[15.5,3.1875,15.75,3.125],"tintindex":0,"rotation":0,"texture":"#0"},"down":{"uv":[15.75,3.1875,16.0,3.125],"tintindex":0,"rotation":0,"texture":"#0"}},"rotation":{"origin":[14.25,13.794117,20.816177],"angle":-22.5,"axis":"z"}},{"from":[-2.5,6.0441175,-2.5588236],"to":[18.5,8.544117,18.441177],"faces":{"east":{"uv":[8.0625,5.375,10.6875,5.6875],"tintindex":0,"rotation":0,"texture":"#0"},"south":{"uv":[8.0625,5.6875,10.6875,6.0],"tintindex":0,"rotation":0,"texture":"#0"},"north":{"uv":[0.875,7.9375,3.5,8.25],"tintindex":0,"rotation":0,"texture":"#0"},"west":{"uv":[8.0625,6.0,10.6875,6.3125],"tintindex":0,"rotation":0,"texture":"#0"},"up":{"uv":[5.625,2.625,3.0,0.0],"tintindex":0,"rotation":0,"texture":"#0"},"down":{"uv":[5.625,2.625,3.0,5.25],"tintindex":0,"rotation":0,"texture":"#0"}}},{"from":[20.0,20.044117,7.4411764],"to":[23.0,22.544117,9.941176],"faces":{"east":{"uv":[4.6875,10.1875,5.0,10.5],"tintindex":0,"rotation":0,"texture":"#0"},"south":{"uv":[10.1875,1.125,10.5625,1.4375],"tintindex":0,"rotation":0,"texture":"#0"},"north":{"uv":[5.625,4.9375,6.0,5.25],"tintindex":0,"rotation":0,"texture":"#0"},"west":{"uv":[5.0,10.1875,5.3125,10.5],"tintindex":0,"rotation":0,"texture":"#0"},"up":{"uv":[10.5625,1.75,10.1875,1.4375],"tintindex":0,"rotation":0,"texture":"#0"},"down":{"uv":[10.5625,1.75,10.1875,2.0625],"tintindex":0,"rotation":0,"texture":"#0"}}},{"from":[-5.0,13.044117,-1.5588236],"to":[-4.0,16.544117,8.941176],"faces":{"east":{"uv":[16.0,3.5625,14.6875,4.0],"tintindex":0,"rotation":0,"texture":"#0"},"south":{"uv":[15.875,4.5625,15.75,5.0],"tintindex":0,"rotation":0,"texture":"#0"},"north":{"uv":[16.0,4.5625,15.875,5.0],"tintindex":0,"rotation":0,"texture":"#0"},"west":{"uv":[16.0,4.0,14.6875,4.4375],"tintindex":0,"rotation":0,"texture":"#0"},"up":{"uv":[14.6875,4.5625,16.0,4.4375],"tintindex":0,"rotation":90,"texture":"#0"},"down":{"uv":[14.6875,3.5625,16.0,3.4375],"tintindex":0,"rotation":270,"texture":"#0"}},"rotation":{"origin":[-8.375,15.294117,5.1911764],"angle":-22.5,"axis":"x"}},{"from":[-8.0,19.044117,6.4411764],"to":[-7.0,23.544117,10.941176],"faces":{"east":{"uv":[10.0,8.0625,9.4375,8.625],"tintindex":0,"rotation":0,"texture":"#0"},"south":{"uv":[6.0,8.0625,5.875,8.625],"tintindex":0,"rotation":0,"texture":"#0"},"north":{"uv":[6.0,7.5,5.875,8.0625],"tintindex":0,"rotation":0,"texture":"#0"},"west":{"uv":[9.875,8.875,9.3125,9.4375],"tintindex":0,"rotation":0,"texture":"#0"},"up":{"uv":[4.0625,9.5625,4.1875,9.0],"tintindex":0,"rotation":0,"texture":"#0"},"down":{"uv":[1.5625,9.0625,1.6875,9.625],"tintindex":0,"rotation":0,"texture":"#0"}}},{"from":[0.5,8.544117,-4.0588236],"to":[6.0,17.044117,-0.5588236],"faces":{"east":{"uv":[1.9375,9.0,2.375,10.0625],"tintindex":0,"rotation":0,"texture":"#0"},"south":{"uv":[8.0625,7.5625,8.75,8.625],"tintindex":0,"rotation":0,"texture":"#0"},"north":{"uv":[3.5,7.9375,4.1875,9.0],"tintindex":0,"rotation":0,"texture":"#0"},"west":{"uv":[2.375,9.0,2.8125,10.0625],"tintindex":0,"rotation":0,"texture":"#0"},"up":{"uv":[10.1875,2.0625,9.5,1.625],"tintindex":0,"rotation":0,"texture":"#0"},"down":{"uv":[6.5625,9.5,5.875,9.9375],"tintindex":0,"rotation":0,"texture":"#0"}}},{"from":[6.0,8.544117,-4.0588236],"to":[10.0,26.544117,-0.5588236],"faces":{"east":{"uv":[0.0,7.8125,0.4375,10.0625],"tintindex":0,"rotation":0,"texture":"#0"},"south":{"uv":[7.125,6.75,7.625,9.0],"tintindex":0,"rotation":0,"texture":"#0"},"north":{"uv":[7.125,4.5,7.625,6.75],"tintindex":0,"rotation":0,"texture":"#0"},"west":{"uv":[0.4375,7.8125,0.875,10.0625],"tintindex":0,"rotation":0,"texture":"#0"},"up":{"uv":[10.5,5.375,10.0,4.9375],"tintindex":0,"rotation":0,"texture":"#0"},"down":{"uv":[0.5,10.0625,0.0,10.5],"tintindex":0,"rotation":0,"texture":"#0"}}},{"from":[-4.0,8.544117,-0.5588236],"to":[20.0,26.544117,19.941177],"faces":{"east":{"uv":[5.625,0.0,8.1875,2.25],"tintindex":0,"rotation":0,"texture":"#0"},"south":{"uv":[3.0,5.25,6.0,7.5],"tintindex":0,"rotation":0,"texture":"#0"},"north":{"uv":[0.0,5.125,3.0,7.375],"tintindex":0,"rotation":0,"texture":"#0"},"west":{"uv":[5.625,2.25,8.1875,4.5],"tintindex":0,"rotation":0,"texture":"#0"},"up":{"uv":[3.0,2.5625,0.0,0.0],"tintindex":0,"rotation":0,"texture":"#0"},"down":{"uv":[3.0,2.5625,0.0,5.125],"tintindex":0,"rotation":0,"texture":"#0"}}},{"from":[9.75,12.794117,20.941177],"to":[11.75,14.794117,21.441177],"faces":{"east":{"uv":[15.375,3.1875,15.3125,3.4375],"tintindex":0,"rotation":0,"texture":"#0"},"south":{"uv":[15.75,3.1875,15.5,3.4375],"tintindex":0,"rotation":0,"texture":"#0"},"north":{"uv":[16.0,3.1875,15.75,3.4375],"tintindex":0,"rotation":0,"texture":"#0"},"west":{"uv":[15.5,3.1875,15.4375,3.4375],"tintindex":0,"rotation":0,"texture":"#0"},"up":{"uv":[15.5,3.1875,15.75,3.125],"tintindex":0,"rotation":0,"texture":"#0"},"down":{"uv":[15.75,3.1875,16.0,3.125],"tintindex":0,"rotation":0,"texture":"#0"}},"rotation":{"origin":[14.25,13.794117,20.816177],"angle":-22.5,"axis":"z"}},{"from":[20.0,12.705923,11.867381],"to":[21.0,16.205923,22.367382],"faces":{"east":{"uv":[14.6875,4.0,16.0,4.4375],"tintindex":0,"rotation":0,"texture":"#0"},"south":{"uv":[15.75,4.5625,15.875,5.0],"tintindex":0,"rotation":0,"texture":"#0"},"north":{"uv":[15.875,4.5625,16.0,5.0],"tintindex":0,"rotation":0,"texture":"#0"},"west":{"uv":[14.6875,3.5625,16.0,4.0],"tintindex":0,"rotation":0,"texture":"#0"},"up":{"uv":[14.6875,4.4375,16.0,4.5625],"tintindex":0,"rotation":90,"texture":"#0"},"down":{"uv":[14.6875,3.4375,16.0,3.5625],"tintindex":0,"rotation":270,"texture":"#0"}},"rotation":{"origin":[20.875,11.955923,14.117381],"angle":-45.0,"axis":"x"}},{"from":[10.0,8.544117,-4.0588236],"to":[15.5,17.044117,-0.5588236],"faces":{"east":{"uv":[2.8125,9.0,3.25,10.0625],"tintindex":0,"rotation":0,"texture":"#0"},"south":{"uv":[8.1875,1.0625,8.875,2.125],"tintindex":0,"rotation":0,"texture":"#0"},"north":{"uv":[8.1875,0.0,8.875,1.0625],"tintindex":0,"rotation":0,"texture":"#0"},"west":{"uv":[3.25,9.0,3.6875,10.0625],"tintindex":0,"rotation":0,"texture":"#0"},"up":{"uv":[10.3125,3.8125,9.625,3.375],"tintindex":0,"rotation":0,"texture":"#0"},"down":{"uv":[8.75,9.625,8.0625,10.0625],"tintindex":0,"rotation":0,"texture":"#0"}}},{"from":[-5.5,10.955923,9.617381],"to":[-5.0,12.955923,11.617381],"faces":{"east":{"uv":[16.0,3.1875,15.75,3.4375],"tintindex":0,"rotation":0,"texture":"#0"},"south":{"uv":[15.375,3.1875,15.3125,3.4375],"tintindex":0,"rotation":0,"texture":"#0"},"north":{"uv":[15.5,3.1875,15.4375,3.4375],"tintindex":0,"rotation":0,"texture":"#0"},"west":{"uv":[15.75,3.1875,15.5,3.4375],"tintindex":0,"rotation":0,"texture":"#0"},"up":{"uv":[15.5,3.1875,15.75,3.125],"tintindex":0,"rotation":90,"texture":"#0"},"down":{"uv":[15.75,3.1875,16.0,3.125],"tintindex":0,"rotation":270,"texture":"#0"}}},{"from":[-5.5,10.955923,16.617382],"to":[-5.0,12.955923,18.617382],"faces":{"east":{"uv":[16.0,3.1875,15.75,3.4375],"tintindex":0,"rotation":0,"texture":"#0"},"south":{"uv":[15.375,3.1875,15.3125,3.4375],"tintindex":0,"rotation":0,"texture":"#0"},"north":{"uv":[15.5,3.1875,15.4375,3.4375],"tintindex":0,"rotation":0,"texture":"#0"},"west":{"uv":[15.75,3.1875,15.5,3.4375],"tintindex":0,"rotation":0,"texture":"#0"},"up":{"uv":[15.5,3.1875,15.75,3.125],"tintindex":0,"rotation":90,"texture":"#0"},"down":{"uv":[15.75,3.1875,16.0,3.125],"tintindex":0,"rotation":270,"texture":"#0"}}},{"from":[-4.0,8.544117,-4.0588236],"to":[0.5,26.544117,-0.5588236],"faces":{"east":{"uv":[4.75,7.5,5.1875,9.75],"tintindex":0,"rotation":0,"texture":"#0"},"south":{"uv":[6.5625,4.5,7.125,6.75],"tintindex":0,"rotation":0,"texture":"#0"},"north":{"uv":[6.0,4.5,6.5625,6.75],"tintindex":0,"rotation":0,"texture":"#0"},"west":{"uv":[5.1875,7.5,5.625,9.75],"tintindex":0,"rotation":0,"texture":"#0"},"up":{"uv":[9.3125,10.0625,8.75,9.625],"tintindex":0,"rotation":0,"texture":"#0"},"down":{"uv":[5.25,9.75,4.6875,10.1875],"tintindex":0,"rotation":0,"texture":"#0"}}},{"from":[20.0,13.044117,-1.5588236],"to":[21.0,16.544117,8.941176],"faces":{"east":{"uv":[14.6875,4.0,16.0,4.4375],"tintindex":0,"rotation":0,"texture":"#0"},"south":{"uv":[15.75,4.5625,15.875,5.0],"tintindex":0,"rotation":0,"texture":"#0"},"north":{"uv":[15.875,4.5625,16.0,5.0],"tintindex":0,"rotation":0,"texture":"#0"},"west":{"uv":[14.6875,3.5625,16.0,4.0],"tintindex":0,"rotation":0,"texture":"#0"},"up":{"uv":[14.6875,4.4375,16.0,4.5625],"tintindex":0,"rotation":90,"texture":"#0"},"down":{"uv":[14.6875,3.4375,16.0,3.5625],"tintindex":0,"rotation":270,"texture":"#0"}},"rotation":{"origin":[24.375,15.294117,5.1911764],"angle":-22.5,"axis":"x"}},{"from":[15.5,8.544117,-4.0588236],"to":[20.0,26.544117,-0.5588236],"faces":{"east":{"uv":[7.625,5.375,8.0625,7.625],"tintindex":0,"rotation":0,"texture":"#0"},"south":{"uv":[6.5625,6.75,7.125,9.0],"tintindex":0,"rotation":0,"texture":"#0"},"north":{"uv":[6.0,6.75,6.5625,9.0],"tintindex":0,"rotation":0,"texture":"#0"},"west":{"uv":[7.625,7.625,8.0625,9.875],"tintindex":0,"rotation":0,"texture":"#0"},"up":{"uv":[6.4375,10.375,5.875,9.9375],"tintindex":0,"rotation":0,"texture":"#0"},"down":{"uv":[7.0,9.9375,6.4375,10.375],"tintindex":0,"rotation":0,"texture":"#0"}}},{"from":[16.5,26.544117,-2.5588236],"to":[18.5,29.044117,18.441177],"faces":{"east":{"uv":[8.0625,6.3125,10.6875,6.625],"tintindex":0,"rotation":0,"texture":"#0"},"south":{"uv":[5.3125,10.1875,5.5625,10.5],"tintindex":0,"rotation":0,"texture":"#0"},"north":{"uv":[5.625,10.125,5.875,10.4375],"tintindex":0,"rotation":0,"texture":"#0"},"west":{"uv":[8.0625,6.625,10.6875,6.9375],"tintindex":0,"rotation":0,"texture":"#0"},"up":{"uv":[5.875,10.125,5.625,7.5],"tintindex":0,"rotation":0,"texture":"#0"},"down":{"uv":[4.4375,7.9375,4.1875,10.5625],"tintindex":0,"rotation":0,"texture":"#0"}}},{"from":[-0.5,26.544117,-2.5588236],"to":[16.5,29.044117,-0.5588236],"faces":{"east":{"uv":[3.0,10.25,3.25,10.5625],"tintindex":0,"rotation":0,"texture":"#0"},"south":{"uv":[8.1875,3.0625,10.3125,3.375],"tintindex":0,"rotation":0,"texture":"#0"},"north":{"uv":[8.1875,2.75,10.3125,3.0625],"tintindex":0,"rotation":0,"texture":"#0"},"west":{"uv":[8.0,10.25,8.25,10.5625],"tintindex":0,"rotation":0,"texture":"#0"},"up":{"uv":[10.875,7.8125,8.75,7.5625],"tintindex":0,"rotation":0,"texture":"#0"},"down":{"uv":[10.875,7.8125,8.75,8.0625],"tintindex":0,"rotation":0,"texture":"#0"}}},{"from":[21.0,13.455923,12.617381],"to":[21.5,15.455923,14.617381],"faces":{"east":{"uv":[15.5,3.1875,15.75,3.4375],"tintindex":0,"rotation":0,"texture":"#0"},"south":{"uv":[15.3125,3.1875,15.375,3.4375],"tintindex":0,"rotation":0,"texture":"#0"},"north":{"uv":[15.4375,3.1875,15.5,3.4375],"tintindex":0,"rotation":0,"texture":"#0"},"west":{"uv":[15.75,3.1875,16.0,3.4375],"tintindex":0,"rotation":0,"texture":"#0"},"up":{"uv":[15.5,3.125,15.75,3.1875],"tintindex":0,"rotation":90,"texture":"#0"},"down":{"uv":[15.75,3.125,16.0,3.1875],"tintindex":0,"rotation":270,"texture":"#0"}},"rotation":{"origin":[20.875,11.955923,14.117381],"angle":-45.0,"axis":"x"}},{"from":[21.0,13.794117,-0.8088236],"to":[21.5,15.794117,1.1911764],"faces":{"east":{"uv":[15.5,3.1875,15.75,3.4375],"tintindex":0,"rotation":0,"texture":"#0"},"south":{"uv":[15.3125,3.1875,15.375,3.4375],"tintindex":0,"rotation":0,"texture":"#0"},"north":{"uv":[15.4375,3.1875,15.5,3.4375],"tintindex":0,"rotation":0,"texture":"#0"},"west":{"uv":[15.75,3.1875,16.0,3.4375],"tintindex":0,"rotation":0,"texture":"#0"},"up":{"uv":[15.5,3.125,15.75,3.1875],"tintindex":0,"rotation":90,"texture":"#0"},"down":{"uv":[15.75,3.125,16.0,3.1875],"tintindex":0,"rotation":270,"texture":"#0"}},"rotation":{"origin":[24.375,15.294117,5.1911764],"angle":-22.5,"axis":"x"}},{"from":[-5.5,13.794117,-0.8088236],"to":[-5.0,15.794117,1.1911764],"faces":{"east":{"uv":[16.0,3.1875,15.75,3.4375],"tintindex":0,"rotation":0,"texture":"#0"},"south":{"uv":[15.375,3.1875,15.3125,3.4375],"tintindex":0,"rotation":0,"texture":"#0"},"north":{"uv":[15.5,3.1875,15.4375,3.4375],"tintindex":0,"rotation":0,"texture":"#0"},"west":{"uv":[15.75,3.1875,15.5,3.4375],"tintindex":0,"rotation":0,"texture":"#0"},"up":{"uv":[15.5,3.1875,15.75,3.125],"tintindex":0,"rotation":90,"texture":"#0"},"down":{"uv":[15.75,3.1875,16.0,3.125],"tintindex":0,"rotation":270,"texture":"#0"}},"rotation":{"origin":[-8.375,15.294117,5.1911764],"angle":-22.5,"axis":"x"}},{"from":[-0.5,26.544117,16.441177],"to":[16.5,29.044117,18.441177],"faces":{"east":{"uv":[10.0,10.1875,10.25,10.5],"tintindex":0,"rotation":0,"texture":"#0"},"south":{"uv":[8.1875,2.4375,10.3125,2.75],"tintindex":0,"rotation":0,"texture":"#0"},"north":{"uv":[8.1875,2.125,10.3125,2.4375],"tintindex":0,"rotation":0,"texture":"#0"},"west":{"uv":[2.75,10.25,3.0,10.5625],"tintindex":0,"rotation":0,"texture":"#0"},"up":{"uv":[10.3125,4.4375,8.1875,4.1875],"tintindex":0,"rotation":0,"texture":"#0"},"down":{"uv":[10.1875,8.625,8.0625,8.875],"tintindex":0,"rotation":0,"texture":"#0"}}},{"from":[-5.0,10.205923,8.867381],"to":[-4.0,13.705923,19.367382],"faces":{"east":{"uv":[16.0,3.5625,14.6875,4.0],"tintindex":0,"rotation":0,"texture":"#0"},"south":{"uv":[15.875,4.5625,15.75,5.0],"tintindex":0,"rotation":0,"texture":"#0"},"north":{"uv":[16.0,4.5625,15.875,5.0],"tintindex":0,"rotation":0,"texture":"#0"},"west":{"uv":[16.0,4.0,14.6875,4.4375],"tintindex":0,"rotation":0,"texture":"#0"},"up":{"uv":[14.6875,4.5625,16.0,4.4375],"tintindex":0,"rotation":90,"texture":"#0"},"down":{"uv":[14.6875,3.5625,16.0,3.4375],"tintindex":0,"rotation":270,"texture":"#0"}}}],"display":{"gui":{"rotation":[30,225,0]}}}